git_gerrit/__about__.py
git_gerrit/__init__.py
git_gerrit/__main__.py
git_gerrit/cli/__init__.py
git_gerrit/cli/checkout.py
git_gerrit/cli/clean.py
git_gerrit/cli/new.py
git_gerrit/cli/push.py
git_gerrit/cli/rebase.py
git_gerrit/cli/status.py
git_gerrit/cli/sync.py
git_gerrit/utils/__init__.py
git_gerrit/utils/branch.py
git_gerrit/utils/change.py
git_gerrit/utils/changebase.py
git_gerrit/utils/gerrit.py
git_gerrit/utils/git.py
git_gerrit/utils/localchange.py
git_gerrit/utils/remotechange.py
git_gerrit/utils/version.py
git_gerrit_bridge-1.2.0.dist-info/METADATA
git_gerrit_bridge-1.2.0.dist-info/WHEEL
git_gerrit_bridge-1.2.0.dist-info/entry_points.txt
git_gerrit_bridge-1.2.0.dist-info/licenses/LICENSE.txt
git_gerrit_bridge-1.2.0.dist-info/RECORD
