Metadata-Version: 2.3
Name: git-gerrit-bridge
Version: 1.2.0
Summary: Git subcommand to ease local branch management with gerrit.
Project-URL: Documentation, https://github.com/Scheirle/git-gerrit-bridget#readme
Project-URL: Issues, https://github.com/Scheirle/git-gerrit-bridge/issues
Project-URL: Source, https://github.com/Scheirle/git-gerrit-bridge
Author-email: Bernhard Scheirle <bernhard@scheirle.de>
License-Expression: GPL-3.0-or-later
License-File: LICENSE.txt
Keywords: gerrit,git
Classifier: Development Status :: 5 - Production/Stable
Classifier: License :: OSI Approved :: GNU General Public License v3 or later (GPLv3+)
Classifier: Programming Language :: Python
Classifier: Programming Language :: Python :: 3
Classifier: Programming Language :: Python :: 3 :: Only
Classifier: Programming Language :: Python :: 3.9
Classifier: Programming Language :: Python :: 3.10
Classifier: Programming Language :: Python :: 3.11
Classifier: Programming Language :: Python :: 3.12
Classifier: Topic :: Software Development :: Version Control :: Git
Requires-Python: >=3.9
Requires-Dist: packaging
Requires-Dist: plumbum
Requires-Dist: requests
Requires-Dist: rich
